{"box_data": [{"position": {"minX": 322.25, "minY": 116.5, "maxX": 334.75, "maxY": 131.125}, "class_id": 0, "box_caption": "nomask 0.720", "scores": {"class_score": 0.7197265625}, "domain": "pixel"}, {"position": {"minX": 249.75, "minY": 106.1875, "maxX": 263.25, "maxY": 121.4375}, "class_id": 0, "box_caption": "nomask 0.692", "scores": {"class_score": 0.69189453125}, "domain": "pixel"}, {"position": {"minX": 74.0, "minY": 116.0, "maxX": 88.875, "maxY": 132.5}, "class_id": 0, "box_caption": "nomask 0.670", "scores": {"class_score": 0.67041015625}, "domain": "pixel"}, {"position": {"minX": 170.75, "minY": 114.0625, "maxX": 184.0, "maxY": 127.4375}, "class_id": 0, "box_caption": "nomask 0.567", "scores": {"class_score": 0.56689453125}, "domain": "pixel"}, {"position": {"minX": 211.625, "minY": 108.625, "maxX": 222.375, "maxY": 121.125}, "class_id": 0, "box_caption": "nomask 0.504", "scores": {"class_score": 0.50439453125}, "domain": "pixel"}, {"position": {"minX": 363.5, "minY": 122.6875, "maxX": 377.5, "maxY": 140.625}, "class_id": 0, "box_caption": "nomask 0.443", "scores": {"class_score": 0.443115234375}, "domain": "pixel"}, {"position": {"minX": 126.375, "minY": 123.875, "maxX": 139.375, "maxY": 137.875}, "class_id": 0, "box_caption": "nomask 0.423", "scores": {"class_score": 0.4228515625}, "domain": "pixel"}, {"position": {"minX": 228.75, "minY": 132.0, "maxX": 240.0, "maxY": 146.5}, "class_id": 0, "box_caption": "nomask 0.396", "scores": {"class_score": 0.39599609375}, "domain": "pixel"}, {"position": {"minX": 506.5, "minY": 114.25, "maxX": 521.5, "maxY": 129.25}, "class_id": 0, "box_caption": "nomask 0.388", "scores": {"class_score": 0.388427734375}, "domain": "pixel"}, {"position": {"minX": 447.75, "minY": 119.6875, "maxX": 456.25, "maxY": 129.875}, "class_id": 0, "box_caption": "nomask 0.362", "scores": {"class_score": 0.36181640625}, "domain": "pixel"}, {"position": {"minX": 289.75, "minY": 116.5, "maxX": 303.25, "maxY": 132.125}, "class_id": 0, "box_caption": "nomask 0.320", "scores": {"class_score": 0.31982421875}, "domain": "pixel"}, {"position": {"minX": 403.25, "minY": 125.25, "maxX": 413.75, "maxY": 137.0}, "class_id": 0, "box_caption": "nomask 0.285", "scores": {"class_score": 0.28466796875}, "domain": "pixel"}, {"position": {"minX": 207.375, "minY": 131.5, "maxX": 221.125, "maxY": 146.25}, "class_id": 0, "box_caption": "nomask 0.255", "scores": {"class_score": 0.254638671875}, "domain": "pixel"}, {"position": {"minX": 276.5, "minY": 128.875, "maxX": 286.0, "maxY": 140.375}, "class_id": 0, "box_caption": "nomask 0.253", "scores": {"class_score": 0.252685546875}, "domain": "pixel"}, {"position": {"minX": 211.5, "minY": 110.8125, "maxX": 223.75, "maxY": 124.1875}, "class_id": 0, "box_caption": "nomask 0.229", "scores": {"class_score": 0.2293701171875}, "domain": "pixel"}, {"position": {"minX": 40.5, "minY": 231.5, "maxX": 61.5625, "maxY": 259.25}, "class_id": 0, "box_caption": "nomask 0.213", "scores": {"class_score": 0.213134765625}, "domain": "pixel"}, {"position": {"minX": 449.25, "minY": 118.9375, "maxX": 458.25, "maxY": 129.0}, "class_id": 0, "box_caption": "nomask 0.205", "scores": {"class_score": 0.204833984375}, "domain": "pixel"}, {"position": {"minX": 84.375, "minY": 148.875, "maxX": 100.0, "maxY": 163.375}, "class_id": 0, "box_caption": "nomask 0.196", "scores": {"class_score": 0.1961669921875}, "domain": "pixel"}, {"position": {"minX": 226.375, "minY": 132.0, "maxX": 241.375, "maxY": 150.25}, "class_id": 0, "box_caption": "nomask 0.186", "scores": {"class_score": 0.18603515625}, "domain": "pixel"}, {"position": {"minX": 536.0, "minY": 138.375, "maxX": 546.0, "maxY": 150.375}, "class_id": 0, "box_caption": "nomask 0.185", "scores": {"class_score": 0.18505859375}, "domain": "pixel"}, {"position": {"minX": 289.75, "minY": 115.8125, "maxX": 300.25, "maxY": 125.9375}, "class_id": 0, "box_caption": "nomask 0.182", "scores": {"class_score": 0.1817626953125}, "domain": "pixel"}, {"position": {"minX": 517.0, "minY": 163.5, "maxX": 530.0, "maxY": 183.0}, "class_id": 0, "box_caption": "nomask 0.178", "scores": {"class_score": 0.178466796875}, "domain": "pixel"}, {"position": {"minX": 364.0, "minY": 123.875, "maxX": 376.0, "maxY": 134.375}, "class_id": 0, "box_caption": "nomask 0.176", "scores": {"class_score": 0.1761474609375}, "domain": "pixel"}, {"position": {"minX": 85.5625, "minY": 149.875, "maxX": 105.4375, "maxY": 172.625}, "class_id": 0, "box_caption": "nomask 0.155", "scores": {"class_score": 0.1553955078125}, "domain": "pixel"}, {"position": {"minX": 206.625, "minY": 134.375, "maxX": 221.625, "maxY": 153.625}, "class_id": 0, "box_caption": "nomask 0.138", "scores": {"class_score": 0.137939453125}, "domain": "pixel"}, {"position": {"minX": 404.25, "minY": 127.75, "maxX": 415.25, "maxY": 142.75}, "class_id": 0, "box_caption": "nomask 0.132", "scores": {"class_score": 0.1319580078125}, "domain": "pixel"}, {"position": {"minX": 50.28125, "minY": 132.25, "maxX": 62.21875, "maxY": 147.0}, "class_id": 0, "box_caption": "nomask 0.130", "scores": {"class_score": 0.1295166015625}, "domain": "pixel"}, {"position": {"minX": 290.0, "minY": 121.8125, "maxX": 304.5, "maxY": 134.875}, "class_id": 0, "box_caption": "nomask 0.126", "scores": {"class_score": 0.1258544921875}, "domain": "pixel"}, {"position": {"minX": 468.0, "minY": 133.625, "maxX": 477.0, "maxY": 144.125}, "class_id": 0, "box_caption": "nomask 0.117", "scores": {"class_score": 0.11663818359375}, "domain": "pixel"}, {"position": {"minX": 421.25, "minY": 127.375, "maxX": 432.75, "maxY": 141.125}, "class_id": 0, "box_caption": "nomask 0.115", "scores": {"class_score": 0.11529541015625}, "domain": "pixel"}, {"position": {"minX": 90.75, "minY": 156.625, "maxX": 107.75, "maxY": 176.625}, "class_id": 0, "box_caption": "nomask 0.099", "scores": {"class_score": 0.09906005859375}, "domain": "pixel"}, {"position": {"minX": 401.5, "minY": 122.5625, "maxX": 410.5, "maxY": 132.25}, "class_id": 0, "box_caption": "nomask 0.088", "scores": {"class_score": 0.08837890625}, "domain": "pixel"}, {"position": {"minX": 320.5, "minY": 116.3125, "maxX": 338.0, "maxY": 134.875}, "class_id": 0, "box_caption": "nomask 0.085", "scores": {"class_score": 0.08544921875}, "domain": "pixel"}, {"position": {"minX": 418.0, "minY": 127.375, "maxX": 431.0, "maxY": 138.875}, "class_id": 0, "box_caption": "nomask 0.079", "scores": {"class_score": 0.07861328125}, "domain": "pixel"}, {"position": {"minX": 389.5, "minY": 138.25, "maxX": 401.5, "maxY": 153.0}, "class_id": 0, "box_caption": "nomask 0.078", "scores": {"class_score": 0.07843017578125}, "domain": "pixel"}, {"position": {"minX": 531.5, "minY": 139.75, "maxX": 544.5, "maxY": 153.75}, "class_id": 0, "box_caption": "nomask 0.075", "scores": {"class_score": 0.0753173828125}, "domain": "pixel"}, {"position": {"minX": 518.5, "minY": 161.125, "maxX": 531.5, "maxY": 179.125}, "class_id": 0, "box_caption": "nomask 0.074", "scores": {"class_score": 0.0738525390625}, "domain": "pixel"}, {"position": {"minX": 210.75, "minY": 109.625, "maxX": 220.5, "maxY": 119.125}, "class_id": 0, "box_caption": "nomask 0.072", "scores": {"class_score": 0.071533203125}, "domain": "pixel"}, {"position": {"minX": 397.75, "minY": 131.875, "maxX": 411.75, "maxY": 147.625}, "class_id": 0, "box_caption": "nomask 0.071", "scores": {"class_score": 0.0714111328125}, "domain": "pixel"}, {"position": {"minX": 459.25, "minY": 147.0, "maxX": 470.25, "maxY": 159.75}, "class_id": 0, "box_caption": "nomask 0.070", "scores": {"class_score": 0.07049560546875}, "domain": "pixel"}, {"position": {"minX": 214.0, "minY": 137.75, "maxX": 228.0, "maxY": 155.5}, "class_id": 0, "box_caption": "nomask 0.069", "scores": {"class_score": 0.06927490234375}, "domain": "pixel"}, {"position": {"minX": 211.875, "minY": 128.25, "maxX": 224.875, "maxY": 140.5}, "class_id": 0, "box_caption": "nomask 0.066", "scores": {"class_score": 0.0660400390625}, "domain": "pixel"}, {"position": {"minX": 386.0, "minY": 140.625, "maxX": 397.0, "maxY": 153.375}, "class_id": 0, "box_caption": "nomask 0.065", "scores": {"class_score": 0.0653076171875}, "domain": "pixel"}, {"position": {"minX": 47.71875, "minY": 131.625, "maxX": 63.03125, "maxY": 151.875}, "class_id": 0, "box_caption": "nomask 0.061", "scores": {"class_score": 0.06109619140625}, "domain": "pixel"}, {"position": {"minX": 209.0, "minY": 132.125, "maxX": 224.25, "maxY": 150.625}, "class_id": 0, "box_caption": "nomask 0.060", "scores": {"class_score": 0.05975341796875}, "domain": "pixel"}, {"position": {"minX": 395.0, "minY": 136.75, "maxX": 406.5, "maxY": 153.25}, "class_id": 0, "box_caption": "nomask 0.059", "scores": {"class_score": 0.05914306640625}, "domain": "pixel"}, {"position": {"minX": 211.875, "minY": 147.125, "maxX": 222.625, "maxY": 162.875}, "class_id": 0, "box_caption": "nomask 0.059", "scores": {"class_score": 0.05889892578125}, "domain": "pixel"}, {"position": {"minX": 446.0, "minY": 160.75, "maxX": 465.0, "maxY": 181.5}, "class_id": 0, "box_caption": "nomask 0.058", "scores": {"class_score": 0.058380126953125}, "domain": "pixel"}, {"position": {"minX": 159.75, "minY": 122.375, "maxX": 169.25, "maxY": 134.125}, "class_id": 0, "box_caption": "nomask 0.057", "scores": {"class_score": 0.057037353515625}, "domain": "pixel"}, {"position": {"minX": 309.75, "minY": 133.125, "maxX": 319.75, "maxY": 145.375}, "class_id": 0, "box_caption": "nomask 0.056", "scores": {"class_score": 0.05621337890625}, "domain": "pixel"}, {"position": {"minX": 392.5, "minY": 136.875, "maxX": 403.0, "maxY": 150.875}, "class_id": 0, "box_caption": "nomask 0.056", "scores": {"class_score": 0.055633544921875}, "domain": "pixel"}, {"position": {"minX": 223.5, "minY": 136.5, "maxX": 236.25, "maxY": 150.0}, "class_id": 0, "box_caption": "nomask 0.055", "scores": {"class_score": 0.054931640625}, "domain": "pixel"}, {"position": {"minX": 93.375, "minY": 154.5, "maxX": 112.625, "maxY": 176.5}, "class_id": 0, "box_caption": "nomask 0.054", "scores": {"class_score": 0.054229736328125}, "domain": "pixel"}, {"position": {"minX": 143.625, "minY": 125.5, "maxX": 153.625, "maxY": 137.0}, "class_id": 0, "box_caption": "nomask 0.053", "scores": {"class_score": 0.053497314453125}, "domain": "pixel"}, {"position": {"minX": 336.75, "minY": 139.0, "maxX": 346.75, "maxY": 150.5}, "class_id": 0, "box_caption": "nomask 0.053", "scores": {"class_score": 0.052734375}, "domain": "pixel"}, {"position": {"minX": 231.625, "minY": 133.5, "maxX": 242.375, "maxY": 145.5}, "class_id": 0, "box_caption": "nomask 0.052", "scores": {"class_score": 0.05181884765625}, "domain": "pixel"}, {"position": {"minX": 461.0, "minY": 138.875, "maxX": 473.5, "maxY": 154.375}, "class_id": 0, "box_caption": "nomask 0.051", "scores": {"class_score": 0.0509033203125}, "domain": "pixel"}, {"position": {"minX": 158.25, "minY": 158.5, "maxX": 172.25, "maxY": 173.75}, "class_id": 0, "box_caption": "nomask 0.050", "scores": {"class_score": 0.050140380859375}, "domain": "pixel"}, {"position": {"minX": 530.5, "minY": 137.875, "maxX": 542.5, "maxY": 150.375}, "class_id": 0, "box_caption": "nomask 0.050", "scores": {"class_score": 0.04962158203125}, "domain": "pixel"}, {"position": {"minX": 250.375, "minY": 109.25, "maxX": 265.75, "maxY": 124.75}, "class_id": 0, "box_caption": "nomask 0.049", "scores": {"class_score": 0.04876708984375}, "domain": "pixel"}, {"position": {"minX": 238.0, "minY": 175.0, "maxX": 250.5, "maxY": 191.5}, "class_id": 0, "box_caption": "nomask 0.048", "scores": {"class_score": 0.047607421875}, "domain": "pixel"}, {"position": {"minX": 15.46875, "minY": 240.875, "maxX": 28.625, "maxY": 260.5}, "class_id": 0, "box_caption": "nomask 0.047", "scores": {"class_score": 0.04730224609375}, "domain": "pixel"}, {"position": {"minX": 53.59375, "minY": 135.0, "maxX": 64.25, "maxY": 150.25}, "class_id": 0, "box_caption": "nomask 0.045", "scores": {"class_score": 0.045135498046875}, "domain": "pixel"}, {"position": {"minX": 507.5, "minY": 118.4375, "maxX": 521.5, "maxY": 133.625}, "class_id": 0, "box_caption": "nomask 0.045", "scores": {"class_score": 0.04473876953125}, "domain": "pixel"}, {"position": {"minX": 99.9375, "minY": 138.125, "maxX": 111.3125, "maxY": 152.125}, "class_id": 0, "box_caption": "nomask 0.041", "scores": {"class_score": 0.04058837890625}, "domain": "pixel"}, {"position": {"minX": 453.5, "minY": 124.25, "maxX": 465.0, "maxY": 135.25}, "class_id": 0, "box_caption": "nomask 0.038", "scores": {"class_score": 0.038421630859375}, "domain": "pixel"}, {"position": {"minX": 79.375, "minY": 116.5625, "maxX": 91.5, "maxY": 130.875}, "class_id": 0, "box_caption": "nomask 0.038", "scores": {"class_score": 0.038238525390625}, "domain": "pixel"}, {"position": {"minX": 208.5, "minY": 108.1875, "maxX": 226.0, "maxY": 125.1875}, "class_id": 0, "box_caption": "nomask 0.038", "scores": {"class_score": 0.037933349609375}, "domain": "pixel"}, {"position": {"minX": 448.0, "minY": 119.6875, "maxX": 460.5, "maxY": 137.625}, "class_id": 0, "box_caption": "nomask 0.034", "scores": {"class_score": 0.034271240234375}, "domain": "pixel"}, {"position": {"minX": 464.0, "minY": 131.0, "maxX": 473.5, "maxY": 141.5}, "class_id": 0, "box_caption": "nomask 0.034", "scores": {"class_score": 0.03387451171875}, "domain": "pixel"}, {"position": {"minX": 223.875, "minY": 128.625, "maxX": 237.625, "maxY": 141.375}, "class_id": 0, "box_caption": "nomask 0.033", "scores": {"class_score": 0.032562255859375}, "domain": "pixel"}, {"position": {"minX": 235.5, "minY": 213.5, "maxX": 251.25, "maxY": 235.5}, "class_id": 0, "box_caption": "nomask 0.031", "scores": {"class_score": 0.0313720703125}, "domain": "pixel"}, {"position": {"minX": 94.375, "minY": 161.375, "maxX": 109.5, "maxY": 175.875}, "class_id": 0, "box_caption": "nomask 0.031", "scores": {"class_score": 0.031341552734375}, "domain": "pixel"}, {"position": {"minX": 457.25, "minY": 143.875, "maxX": 470.25, "maxY": 156.625}, "class_id": 0, "box_caption": "nomask 0.031", "scores": {"class_score": 0.0311737060546875}, "domain": "pixel"}, {"position": {"minX": 324.5, "minY": 150.0, "maxX": 334.5, "maxY": 162.75}, "class_id": 0, "box_caption": "nomask 0.031", "scores": {"class_score": 0.03106689453125}, "domain": "pixel"}, {"position": {"minX": 163.75, "minY": 160.625, "maxX": 173.75, "maxY": 173.625}, "class_id": 0, "box_caption": "nomask 0.031", "scores": {"class_score": 0.0308685302734375}, "domain": "pixel"}, {"position": {"minX": 409.75, "minY": 125.4375, "maxX": 427.75, "maxY": 142.75}, "class_id": 0, "box_caption": "nomask 0.030", "scores": {"class_score": 0.030059814453125}, "domain": "pixel"}, {"position": {"minX": 47.375, "minY": 130.375, "maxX": 60.875, "maxY": 145.375}, "class_id": 0, "box_caption": "nomask 0.030", "scores": {"class_score": 0.0300445556640625}, "domain": "pixel"}, {"position": {"minX": 446.75, "minY": 118.1875, "maxX": 458.25, "maxY": 134.0}, "class_id": 0, "box_caption": "nomask 0.030", "scores": {"class_score": 0.02996826171875}, "domain": "pixel"}, {"position": {"minX": 367.25, "minY": 125.0625, "maxX": 382.25, "maxY": 142.0}, "class_id": 0, "box_caption": "nomask 0.030", "scores": {"class_score": 0.02984619140625}, "domain": "pixel"}, {"position": {"minX": 619.0, "minY": 135.125, "maxX": 639.0, "maxY": 158.125}, "class_id": 0, "box_caption": "nomask 0.030", "scores": {"class_score": 0.0297393798828125}, "domain": "pixel"}, {"position": {"minX": 457.0, "minY": 132.875, "maxX": 468.5, "maxY": 143.625}, "class_id": 0, "box_caption": "nomask 0.030", "scores": {"class_score": 0.0297088623046875}, "domain": "pixel"}, {"position": {"minX": 128.75, "minY": 164.125, "maxX": 139.25, "maxY": 175.375}, "class_id": 0, "box_caption": "nomask 0.029", "scores": {"class_score": 0.0294952392578125}, "domain": "pixel"}, {"position": {"minX": 287.0, "minY": 118.125, "maxX": 306.0, "maxY": 137.125}, "class_id": 0, "box_caption": "nomask 0.029", "scores": {"class_score": 0.0292205810546875}, "domain": "pixel"}, {"position": {"minX": 73.0625, "minY": 110.0, "maxX": 91.1875, "maxY": 138.5}, "class_id": 0, "box_caption": "nomask 0.029", "scores": {"class_score": 0.0287628173828125}, "domain": "pixel"}, {"position": {"minX": 432.5, "minY": 140.5, "maxX": 443.0, "maxY": 154.75}, "class_id": 0, "box_caption": "nomask 0.029", "scores": {"class_score": 0.0286102294921875}, "domain": "pixel"}, {"position": {"minX": 417.0, "minY": 131.0, "maxX": 429.5, "maxY": 143.0}, "class_id": 0, "box_caption": "nomask 0.027", "scores": {"class_score": 0.02703857421875}, "domain": "pixel"}, {"position": {"minX": 14.390625, "minY": 244.25, "maxX": 27.296875, "maxY": 264.75}, "class_id": 0, "box_caption": "nomask 0.027", "scores": {"class_score": 0.02703857421875}, "domain": "pixel"}, {"position": {"minX": 512.5, "minY": 113.3125, "maxX": 524.5, "maxY": 125.1875}, "class_id": 0, "box_caption": "nomask 0.027", "scores": {"class_score": 0.0269927978515625}, "domain": "pixel"}, {"position": {"minX": 385.25, "minY": 144.875, "maxX": 396.25, "maxY": 157.375}, "class_id": 0, "box_caption": "nomask 0.027", "scores": {"class_score": 0.0269927978515625}, "domain": "pixel"}, {"position": {"minX": 372.75, "minY": 132.0, "maxX": 385.75, "maxY": 145.75}, "class_id": 0, "box_caption": "nomask 0.027", "scores": {"class_score": 0.0268096923828125}, "domain": "pixel"}, {"position": {"minX": 384.0, "minY": 136.875, "maxX": 394.5, "maxY": 149.625}, "class_id": 0, "box_caption": "nomask 0.027", "scores": {"class_score": 0.026611328125}, "domain": "pixel"}, {"position": {"minX": 171.625, "minY": 118.5, "maxX": 184.625, "maxY": 132.0}, "class_id": 0, "box_caption": "nomask 0.026", "scores": {"class_score": 0.0260772705078125}, "domain": "pixel"}, {"position": {"minX": 97.375, "minY": 135.75, "maxX": 110.5, "maxY": 148.25}, "class_id": 0, "box_caption": "nomask 0.025", "scores": {"class_score": 0.025421142578125}, "domain": "pixel"}, {"position": {"minX": 537.0, "minY": 136.25, "maxX": 546.0, "maxY": 146.5}, "class_id": 0, "box_caption": "nomask 0.024", "scores": {"class_score": 0.0243682861328125}, "domain": "pixel"}, {"position": {"minX": 154.125, "minY": 119.0625, "maxX": 166.875, "maxY": 130.625}, "class_id": 0, "box_caption": "nomask 0.023", "scores": {"class_score": 0.02349853515625}, "domain": "pixel"}, {"position": {"minX": 515.0, "minY": 161.5, "maxX": 535.0, "maxY": 184.25}, "class_id": 0, "box_caption": "nomask 0.023", "scores": {"class_score": 0.0233917236328125}, "domain": "pixel"}, {"position": {"minX": 154.125, "minY": 157.75, "maxX": 168.875, "maxY": 173.5}, "class_id": 0, "box_caption": "nomask 0.023", "scores": {"class_score": 0.023162841796875}, "domain": "pixel"}, {"position": {"minX": 312.0, "minY": 130.625, "maxX": 321.5, "maxY": 140.625}, "class_id": 0, "box_caption": "nomask 0.022", "scores": {"class_score": 0.0224456787109375}, "domain": "pixel"}, {"position": {"minX": 195.125, "minY": 162.125, "maxX": 217.375, "maxY": 202.375}, "class_id": 0, "box_caption": "nomask 0.022", "scores": {"class_score": 0.02227783203125}, "domain": "pixel"}, {"position": {"minX": 302.0, "minY": 123.625, "maxX": 311.5, "maxY": 134.625}, "class_id": 0, "box_caption": "nomask 0.022", "scores": {"class_score": 0.0221710205078125}, "domain": "pixel"}, {"position": {"minX": 94.0, "minY": 140.625, "maxX": 107.75, "maxY": 154.375}, "class_id": 0, "box_caption": "nomask 0.022", "scores": {"class_score": 0.0218658447265625}, "domain": "pixel"}, {"position": {"minX": 445.75, "minY": 124.1875, "maxX": 454.25, "maxY": 134.125}, "class_id": 0, "box_caption": "nomask 0.022", "scores": {"class_score": 0.0218505859375}, "domain": "pixel"}, {"position": {"minX": 431.25, "minY": 134.625, "maxX": 442.25, "maxY": 145.875}, "class_id": 0, "box_caption": "nomask 0.022", "scores": {"class_score": 0.021759033203125}, "domain": "pixel"}, {"position": {"minX": 144.875, "minY": 123.125, "maxX": 154.125, "maxY": 132.875}, "class_id": 0, "box_caption": "nomask 0.021", "scores": {"class_score": 0.0208587646484375}, "domain": "pixel"}, {"position": {"minX": 309.25, "minY": 138.0, "maxX": 320.25, "maxY": 150.25}, "class_id": 0, "box_caption": "nomask 0.021", "scores": {"class_score": 0.020843505859375}, "domain": "pixel"}, {"position": {"minX": 301.25, "minY": 120.4375, "maxX": 309.25, "maxY": 130.25}, "class_id": 0, "box_caption": "nomask 0.021", "scores": {"class_score": 0.0205078125}, "domain": "pixel"}, {"position": {"minX": 179.125, "minY": 195.875, "maxX": 189.625, "maxY": 207.625}, "class_id": 0, "box_caption": "nomask 0.020", "scores": {"class_score": 0.02008056640625}, "domain": "pixel"}, {"position": {"minX": 362.25, "minY": 126.4375, "maxX": 375.25, "maxY": 142.5}, "class_id": 0, "box_caption": "nomask 0.020", "scores": {"class_score": 0.0196685791015625}, "domain": "pixel"}, {"position": {"minX": 292.75, "minY": 116.375, "maxX": 314.25, "maxY": 132.375}, "class_id": 0, "box_caption": "nomask 0.019", "scores": {"class_score": 0.0192718505859375}, "domain": "pixel"}, {"position": {"minX": 529.5, "minY": 136.375, "maxX": 548.5, "maxY": 156.125}, "class_id": 0, "box_caption": "nomask 0.019", "scores": {"class_score": 0.01904296875}, "domain": "pixel"}, {"position": {"minX": 403.75, "minY": 136.625, "maxX": 420.75, "maxY": 155.375}, "class_id": 0, "box_caption": "nomask 0.019", "scores": {"class_score": 0.018951416015625}, "domain": "pixel"}, {"position": {"minX": 524.0, "minY": 141.375, "maxX": 535.0, "maxY": 154.125}, "class_id": 0, "box_caption": "nomask 0.019", "scores": {"class_score": 0.0187225341796875}, "domain": "pixel"}, {"position": {"minX": 458.0, "minY": 138.5, "maxX": 472.0, "maxY": 158.25}, "class_id": 0, "box_caption": "nomask 0.019", "scores": {"class_score": 0.018707275390625}, "domain": "pixel"}, {"position": {"minX": 533.0, "minY": 142.0, "maxX": 546.0, "maxY": 158.5}, "class_id": 0, "box_caption": "nomask 0.019", "scores": {"class_score": 0.0186614990234375}, "domain": "pixel"}, {"position": {"minX": 144.875, "minY": 130.75, "maxX": 156.625, "maxY": 143.25}, "class_id": 0, "box_caption": "nomask 0.018", "scores": {"class_score": 0.0184783935546875}, "domain": "pixel"}, {"position": {"minX": 169.125, "minY": 113.625, "maxX": 186.875, "maxY": 133.0}, "class_id": 0, "box_caption": "nomask 0.018", "scores": {"class_score": 0.018280029296875}, "domain": "pixel"}, {"position": {"minX": 304.5, "minY": 140.75, "maxX": 317.5, "maxY": 154.75}, "class_id": 0, "box_caption": "nomask 0.018", "scores": {"class_score": 0.01824951171875}, "domain": "pixel"}, {"position": {"minX": 41.5, "minY": 132.5, "maxX": 56.125, "maxY": 147.0}, "class_id": 0, "box_caption": "nomask 0.018", "scores": {"class_score": 0.018035888671875}, "domain": "pixel"}, {"position": {"minX": 396.25, "minY": 133.625, "maxX": 411.75, "maxY": 153.875}, "class_id": 0, "box_caption": "nomask 0.018", "scores": {"class_score": 0.01788330078125}, "domain": "pixel"}, {"position": {"minX": 154.25, "minY": 155.125, "maxX": 174.25, "maxY": 181.375}, "class_id": 0, "box_caption": "nomask 0.018", "scores": {"class_score": 0.017608642578125}, "domain": "pixel"}, {"position": {"minX": 83.6875, "minY": 114.25, "maxX": 93.0625, "maxY": 125.75}, "class_id": 0, "box_caption": "nomask 0.018", "scores": {"class_score": 0.0175323486328125}, "domain": "pixel"}, {"position": {"minX": 455.5, "minY": 147.625, "maxX": 469.5, "maxY": 161.875}, "class_id": 0, "box_caption": "nomask 0.018", "scores": {"class_score": 0.0175323486328125}, "domain": "pixel"}, {"position": {"minX": 52.28125, "minY": 212.375, "maxX": 58.96875, "maxY": 222.625}, "class_id": 0, "box_caption": "nomask 0.017", "scores": {"class_score": 0.01708984375}, "domain": "pixel"}, {"position": {"minX": 164.75, "minY": 115.25, "maxX": 181.25, "maxY": 134.75}, "class_id": 0, "box_caption": "nomask 0.017", "scores": {"class_score": 0.0169830322265625}, "domain": "pixel"}, {"position": {"minX": 129.625, "minY": 121.5, "maxX": 145.125, "maxY": 136.25}, "class_id": 0, "box_caption": "nomask 0.017", "scores": {"class_score": 0.0167236328125}, "domain": "pixel"}, {"position": {"minX": 96.875, "minY": 146.125, "maxX": 112.0, "maxY": 163.125}, "class_id": 0, "box_caption": "nomask 0.017", "scores": {"class_score": 0.0167236328125}, "domain": "pixel"}, {"position": {"minX": 91.8125, "minY": 160.0, "maxX": 109.1875, "maxY": 181.75}, "class_id": 0, "box_caption": "nomask 0.017", "scores": {"class_score": 0.016632080078125}, "domain": "pixel"}, {"position": {"minX": 318.5, "minY": 130.625, "maxX": 332.0, "maxY": 142.875}, "class_id": 0, "box_caption": "nomask 0.017", "scores": {"class_score": 0.0165252685546875}, "domain": "pixel"}, {"position": {"minX": 447.25, "minY": 156.5, "maxX": 465.25, "maxY": 175.75}, "class_id": 0, "box_caption": "nomask 0.016", "scores": {"class_score": 0.0164642333984375}, "domain": "pixel"}, {"position": {"minX": 277.25, "minY": 123.9375, "maxX": 291.75, "maxY": 142.75}, "class_id": 0, "box_caption": "nomask 0.016", "scores": {"class_score": 0.0163726806640625}, "domain": "pixel"}, {"position": {"minX": 171.0, "minY": 112.5625, "maxX": 183.75, "maxY": 126.8125}, "class_id": 1, "box_caption": "mask 0.016", "scores": {"class_score": 0.015960693359375}, "domain": "pixel"}, {"position": {"minX": 17.796875, "minY": 235.75, "maxX": 33.21875, "maxY": 253.5}, "class_id": 0, "box_caption": "nomask 0.016", "scores": {"class_score": 0.0157928466796875}, "domain": "pixel"}, {"position": {"minX": 167.0, "minY": 119.4375, "maxX": 180.5, "maxY": 133.125}, "class_id": 0, "box_caption": "nomask 0.016", "scores": {"class_score": 0.0156097412109375}, "domain": "pixel"}, {"position": {"minX": 134.5, "minY": 125.1875, "maxX": 153.25, "maxY": 143.375}, "class_id": 0, "box_caption": "nomask 0.016", "scores": {"class_score": 0.01557159423828125}, "domain": "pixel"}, {"position": {"minX": 396.0, "minY": 126.8125, "maxX": 405.5, "maxY": 136.125}, "class_id": 0, "box_caption": "nomask 0.015", "scores": {"class_score": 0.01537322998046875}, "domain": "pixel"}, {"position": {"minX": 282.5, "minY": 121.375, "maxX": 293.0, "maxY": 131.5}, "class_id": 0, "box_caption": "nomask 0.015", "scores": {"class_score": 0.01514434814453125}, "domain": "pixel"}, {"position": {"minX": 156.0, "minY": 160.25, "maxX": 173.75, "maxY": 177.75}, "class_id": 0, "box_caption": "nomask 0.015", "scores": {"class_score": 0.01506805419921875}, "domain": "pixel"}, {"position": {"minX": 51.6875, "minY": 212.625, "maxX": 61.0, "maxY": 224.625}, "class_id": 0, "box_caption": "nomask 0.015", "scores": {"class_score": 0.01493072509765625}, "domain": "pixel"}, {"position": {"minX": 467.5, "minY": 135.75, "maxX": 478.0, "maxY": 149.5}, "class_id": 0, "box_caption": "nomask 0.015", "scores": {"class_score": 0.0148773193359375}, "domain": "pixel"}, {"position": {"minX": 431.5, "minY": 146.0, "maxX": 442.5, "maxY": 161.5}, "class_id": 0, "box_caption": "nomask 0.015", "scores": {"class_score": 0.01461029052734375}, "domain": "pixel"}, {"position": {"minX": 449.0, "minY": 133.125, "maxX": 459.5, "maxY": 144.875}, "class_id": 0, "box_caption": "nomask 0.015", "scores": {"class_score": 0.01458740234375}, "domain": "pixel"}, {"position": {"minX": 206.125, "minY": 110.3125, "maxX": 220.875, "maxY": 127.0625}, "class_id": 0, "box_caption": "nomask 0.015", "scores": {"class_score": 0.01458740234375}, "domain": "pixel"}, {"position": {"minX": 391.0, "minY": 132.375, "maxX": 406.5, "maxY": 151.625}, "class_id": 0, "box_caption": "nomask 0.014", "scores": {"class_score": 0.01434326171875}, "domain": "pixel"}, {"position": {"minX": 119.875, "minY": 165.75, "maxX": 129.125, "maxY": 178.0}, "class_id": 0, "box_caption": "nomask 0.014", "scores": {"class_score": 0.01413726806640625}, "domain": "pixel"}, {"position": {"minX": 50.625, "minY": 211.875, "maxX": 58.25, "maxY": 220.625}, "class_id": 0, "box_caption": "nomask 0.014", "scores": {"class_score": 0.01413726806640625}, "domain": "pixel"}, {"position": {"minX": 396.0, "minY": 120.9375, "maxX": 405.0, "maxY": 130.75}, "class_id": 0, "box_caption": "nomask 0.014", "scores": {"class_score": 0.01409149169921875}, "domain": "pixel"}, {"position": {"minX": 249.125, "minY": 101.875, "maxX": 266.25, "maxY": 129.875}, "class_id": 0, "box_caption": "nomask 0.014", "scores": {"class_score": 0.014068603515625}, "domain": "pixel"}, {"position": {"minX": 118.1875, "minY": 170.875, "maxX": 127.4375, "maxY": 183.125}, "class_id": 0, "box_caption": "nomask 0.014", "scores": {"class_score": 0.014007568359375}, "domain": "pixel"}, {"position": {"minX": 506.25, "minY": 119.6875, "maxX": 517.5, "maxY": 132.75}, "class_id": 0, "box_caption": "nomask 0.014", "scores": {"class_score": 0.01381683349609375}, "domain": "pixel"}, {"position": {"minX": 376.75, "minY": 139.5, "maxX": 389.75, "maxY": 151.25}, "class_id": 0, "box_caption": "nomask 0.014", "scores": {"class_score": 0.01371002197265625}, "domain": "pixel"}, {"position": {"minX": 528.5, "minY": 144.25, "maxX": 539.5, "maxY": 159.0}, "class_id": 0, "box_caption": "nomask 0.014", "scores": {"class_score": 0.0135955810546875}, "domain": "pixel"}, {"position": {"minX": 469.25, "minY": 131.25, "maxX": 477.75, "maxY": 142.75}, "class_id": 0, "box_caption": "nomask 0.014", "scores": {"class_score": 0.0135650634765625}, "domain": "pixel"}, {"position": {"minX": 368.75, "minY": 131.875, "maxX": 387.75, "maxY": 151.625}, "class_id": 0, "box_caption": "nomask 0.014", "scores": {"class_score": 0.01355743408203125}, "domain": "pixel"}, {"position": {"minX": 529.5, "minY": 196.125, "maxX": 537.5, "maxY": 205.125}, "class_id": 0, "box_caption": "nomask 0.014", "scores": {"class_score": 0.013519287109375}, "domain": "pixel"}, {"position": {"minX": 184.25, "minY": 156.125, "maxX": 194.25, "maxY": 172.875}, "class_id": 0, "box_caption": "nomask 0.013", "scores": {"class_score": 0.01331329345703125}, "domain": "pixel"}, {"position": {"minX": 324.5, "minY": 130.5, "maxX": 335.5, "maxY": 142.75}, "class_id": 0, "box_caption": "nomask 0.013", "scores": {"class_score": 0.0132293701171875}, "domain": "pixel"}, {"position": {"minX": 402.75, "minY": 115.25, "maxX": 411.25, "maxY": 123.25}, "class_id": 0, "box_caption": "nomask 0.013", "scores": {"class_score": 0.013214111328125}, "domain": "pixel"}, {"position": {"minX": 20.9375, "minY": 226.625, "maxX": 37.78125, "maxY": 245.125}, "class_id": 0, "box_caption": "nomask 0.013", "scores": {"class_score": 0.01311492919921875}, "domain": "pixel"}, {"position": {"minX": 203.125, "minY": 132.5, "maxX": 218.125, "maxY": 146.25}, "class_id": 0, "box_caption": "nomask 0.013", "scores": {"class_score": 0.0129547119140625}, "domain": "pixel"}, {"position": {"minX": 127.3125, "minY": 144.875, "maxX": 138.25, "maxY": 158.375}, "class_id": 0, "box_caption": "nomask 0.013", "scores": {"class_score": 0.0129241943359375}, "domain": "pixel"}, {"position": {"minX": 368.0, "minY": 136.875, "maxX": 381.5, "maxY": 149.625}, "class_id": 0, "box_caption": "nomask 0.013", "scores": {"class_score": 0.01275634765625}, "domain": "pixel"}, {"position": {"minX": 183.5, "minY": 150.5, "maxX": 194.75, "maxY": 165.0}, "class_id": 0, "box_caption": "nomask 0.013", "scores": {"class_score": 0.01268768310546875}, "domain": "pixel"}, {"position": {"minX": 308.25, "minY": 126.8125, "maxX": 328.25, "maxY": 144.875}, "class_id": 0, "box_caption": "nomask 0.012", "scores": {"class_score": 0.0124664306640625}, "domain": "pixel"}, {"position": {"minX": 199.75, "minY": 163.625, "maxX": 214.75, "maxY": 183.125}, "class_id": 0, "box_caption": "nomask 0.012", "scores": {"class_score": 0.01242828369140625}, "domain": "pixel"}, {"position": {"minX": 219.75, "minY": 112.625, "maxX": 228.5, "maxY": 121.625}, "class_id": 0, "box_caption": "nomask 0.012", "scores": {"class_score": 0.01232147216796875}, "domain": "pixel"}, {"position": {"minX": 194.25, "minY": 154.375, "maxX": 211.5, "maxY": 173.125}, "class_id": 0, "box_caption": "nomask 0.012", "scores": {"class_score": 0.0121917724609375}, "domain": "pixel"}, {"position": {"minX": 428.25, "minY": 128.75, "maxX": 438.75, "maxY": 139.5}, "class_id": 0, "box_caption": "nomask 0.012", "scores": {"class_score": 0.0120697021484375}, "domain": "pixel"}, {"position": {"minX": 434.75, "minY": 133.0, "maxX": 448.25, "maxY": 146.5}, "class_id": 0, "box_caption": "nomask 0.012", "scores": {"class_score": 0.0120391845703125}, "domain": "pixel"}, {"position": {"minX": 301.0, "minY": 143.75, "maxX": 316.0, "maxY": 160.0}, "class_id": 0, "box_caption": "nomask 0.012", "scores": {"class_score": 0.01202392578125}, "domain": "pixel"}, {"position": {"minX": 321.0, "minY": 112.8125, "maxX": 339.0, "maxY": 141.875}, "class_id": 0, "box_caption": "nomask 0.012", "scores": {"class_score": 0.011993408203125}, "domain": "pixel"}, {"position": {"minX": 194.875, "minY": 158.5, "maxX": 216.875, "maxY": 187.75}, "class_id": 0, "box_caption": "nomask 0.012", "scores": {"class_score": 0.01180267333984375}, "domain": "pixel"}, {"position": {"minX": 291.5, "minY": 126.4375, "maxX": 307.0, "maxY": 142.375}, "class_id": 0, "box_caption": "nomask 0.012", "scores": {"class_score": 0.0117645263671875}, "domain": "pixel"}, {"position": {"minX": 283.5, "minY": 118.4375, "maxX": 299.5, "maxY": 135.5}, "class_id": 0, "box_caption": "nomask 0.012", "scores": {"class_score": 0.01174163818359375}, "domain": "pixel"}, {"position": {"minX": 278.75, "minY": 154.875, "maxX": 288.75, "maxY": 169.375}, "class_id": 0, "box_caption": "nomask 0.012", "scores": {"class_score": 0.01161956787109375}, "domain": "pixel"}, {"position": {"minX": 146.75, "minY": 131.125, "maxX": 161.0, "maxY": 144.875}, "class_id": 0, "box_caption": "nomask 0.012", "scores": {"class_score": 0.0115966796875}, "domain": "pixel"}, {"position": {"minX": 389.25, "minY": 146.875, "maxX": 400.25, "maxY": 158.375}, "class_id": 0, "box_caption": "nomask 0.011", "scores": {"class_score": 0.011474609375}, "domain": "pixel"}, {"position": {"minX": 520.5, "minY": 144.0, "maxX": 536.5, "maxY": 168.25}, "class_id": 0, "box_caption": "nomask 0.011", "scores": {"class_score": 0.011383056640625}, "domain": "pixel"}, {"position": {"minX": 150.125, "minY": 126.0, "maxX": 162.875, "maxY": 138.0}, "class_id": 0, "box_caption": "nomask 0.011", "scores": {"class_score": 0.01134490966796875}, "domain": "pixel"}, {"position": {"minX": 363.5, "minY": 122.6875, "maxX": 377.5, "maxY": 140.625}, "class_id": 1, "box_caption": "mask 0.011", "scores": {"class_score": 0.01134490966796875}, "domain": "pixel"}, {"position": {"minX": 615.0, "minY": 138.25, "maxX": 634.0, "maxY": 156.75}, "class_id": 0, "box_caption": "nomask 0.011", "scores": {"class_score": 0.01122283935546875}, "domain": "pixel"}, {"position": {"minX": 253.5, "minY": 166.0, "maxX": 265.5, "maxY": 177.75}, "class_id": 0, "box_caption": "nomask 0.011", "scores": {"class_score": 0.01117706298828125}, "domain": "pixel"}, {"position": {"minX": 328.25, "minY": 139.875, "maxX": 341.75, "maxY": 156.375}, "class_id": 0, "box_caption": "nomask 0.011", "scores": {"class_score": 0.0110626220703125}, "domain": "pixel"}, {"position": {"minX": 236.125, "minY": 178.25, "maxX": 247.125, "maxY": 195.75}, "class_id": 0, "box_caption": "nomask 0.011", "scores": {"class_score": 0.01105499267578125}, "domain": "pixel"}, {"position": {"minX": 151.875, "minY": 155.875, "maxX": 176.625, "maxY": 195.125}, "class_id": 0, "box_caption": "nomask 0.011", "scores": {"class_score": 0.0106964111328125}, "domain": "pixel"}, {"position": {"minX": 119.5, "minY": 163.375, "maxX": 128.375, "maxY": 173.875}, "class_id": 0, "box_caption": "nomask 0.011", "scores": {"class_score": 0.01058197021484375}, "domain": "pixel"}, {"position": {"minX": 188.875, "minY": 153.375, "maxX": 205.125, "maxY": 172.125}, "class_id": 0, "box_caption": "nomask 0.010", "scores": {"class_score": 0.0104217529296875}, "domain": "pixel"}, {"position": {"minX": 370.5, "minY": 121.375, "maxX": 379.5, "maxY": 129.625}, "class_id": 0, "box_caption": "nomask 0.010", "scores": {"class_score": 0.01039886474609375}, "domain": "pixel"}, {"position": {"minX": 626.0, "minY": 200.125, "maxX": 649.0, "maxY": 223.875}, "class_id": 0, "box_caption": "nomask 0.010", "scores": {"class_score": 0.01039886474609375}, "domain": "pixel"}, {"position": {"minX": 233.5, "minY": 202.0, "maxX": 243.0, "maxY": 213.25}, "class_id": 0, "box_caption": "nomask 0.010", "scores": {"class_score": 0.0103759765625}, "domain": "pixel"}, {"position": {"minX": 212.625, "minY": 151.625, "maxX": 223.125, "maxY": 165.375}, "class_id": 0, "box_caption": "nomask 0.010", "scores": {"class_score": 0.01020050048828125}, "domain": "pixel"}, {"position": {"minX": 447.0, "minY": 139.125, "maxX": 459.0, "maxY": 153.375}, "class_id": 0, "box_caption": "nomask 0.010", "scores": {"class_score": 0.01015472412109375}, "domain": "pixel"}, {"position": {"minX": 25.65625, "minY": 224.5, "maxX": 55.59375, "maxY": 255.25}, "class_id": 0, "box_caption": "nomask 0.010", "scores": {"class_score": 0.0101470947265625}, "domain": "pixel"}, {"position": {"minX": 464.25, "minY": 131.0, "maxX": 477.75, "maxY": 149.25}, "class_id": 0, "box_caption": "nomask 0.010", "scores": {"class_score": 0.0101165771484375}, "domain": "pixel"}, {"position": {"minX": 95.8125, "minY": 135.0, "maxX": 110.1875, "maxY": 153.75}, "class_id": 0, "box_caption": "nomask 0.010", "scores": {"class_score": 0.0100250244140625}, "domain": "pixel"}, {"position": {"minX": 224.375, "minY": 128.625, "maxX": 244.375, "maxY": 157.375}, "class_id": 0, "box_caption": "nomask 0.010", "scores": {"class_score": 0.0100250244140625}, "domain": "pixel"}, {"position": {"minX": 458.25, "minY": 120.4375, "maxX": 469.75, "maxY": 129.5}, "class_id": 0, "box_caption": "nomask 0.010", "scores": {"class_score": 0.009979248046875}, "domain": "pixel"}, {"position": {"minX": 240.0, "minY": 177.375, "maxX": 251.75, "maxY": 194.625}, "class_id": 0, "box_caption": "nomask 0.010", "scores": {"class_score": 0.00995635986328125}, "domain": "pixel"}, {"position": {"minX": 52.21875, "minY": 210.875, "maxX": 62.28125, "maxY": 221.625}, "class_id": 0, "box_caption": "nomask 0.010", "scores": {"class_score": 0.00991058349609375}, "domain": "pixel"}, {"position": {"minX": 20.953125, "minY": 194.875, "maxX": 33.0, "maxY": 208.375}, "class_id": 0, "box_caption": "nomask 0.010", "scores": {"class_score": 0.0099029541015625}, "domain": "pixel"}, {"position": {"minX": 276.5, "minY": 149.625, "maxX": 288.0, "maxY": 164.125}, "class_id": 0, "box_caption": "nomask 0.010", "scores": {"class_score": 0.00981903076171875}, "domain": "pixel"}, {"position": {"minX": 448.5, "minY": 151.125, "maxX": 462.0, "maxY": 165.125}, "class_id": 0, "box_caption": "nomask 0.010", "scores": {"class_score": 0.00972747802734375}, "domain": "pixel"}, {"position": {"minX": 69.125, "minY": 117.3125, "maxX": 80.875, "maxY": 131.0}, "class_id": 0, "box_caption": "nomask 0.010", "scores": {"class_score": 0.0096435546875}, "domain": "pixel"}, {"position": {"minX": 416.0, "minY": 122.25, "maxX": 428.0, "maxY": 132.125}, "class_id": 0, "box_caption": "nomask 0.010", "scores": {"class_score": 0.00962066650390625}, "domain": "pixel"}, {"position": {"minX": 625.5, "minY": 137.0, "maxX": 638.5, "maxY": 157.0}, "class_id": 0, "box_caption": "nomask 0.009", "scores": {"class_score": 0.00927734375}, "domain": "pixel"}, {"position": {"minX": 188.0, "minY": 147.375, "maxX": 204.0, "maxY": 167.625}, "class_id": 0, "box_caption": "nomask 0.009", "scores": {"class_score": 0.0092620849609375}, "domain": "pixel"}, {"position": {"minX": 426.25, "minY": 127.8125, "maxX": 444.75, "maxY": 144.75}, "class_id": 0, "box_caption": "nomask 0.009", "scores": {"class_score": 0.0090789794921875}, "domain": "pixel"}, {"position": {"minX": 224.25, "minY": 118.4375, "maxX": 233.5, "maxY": 128.625}, "class_id": 0, "box_caption": "nomask 0.009", "scores": {"class_score": 0.00902557373046875}, "domain": "pixel"}, {"position": {"minX": 131.0, "minY": 128.25, "maxX": 145.75, "maxY": 143.25}, "class_id": 0, "box_caption": "nomask 0.009", "scores": {"class_score": 0.0089569091796875}, "domain": "pixel"}, {"position": {"minX": 74.0, "minY": 116.0, "maxX": 88.875, "maxY": 132.5}, "class_id": 1, "box_caption": "mask 0.009", "scores": {"class_score": 0.00887298583984375}, "domain": "pixel"}, {"position": {"minX": 324.25, "minY": 154.0, "maxX": 335.25, "maxY": 167.5}, "class_id": 0, "box_caption": "nomask 0.009", "scores": {"class_score": 0.00884246826171875}, "domain": "pixel"}, {"position": {"minX": 435.0, "minY": 138.375, "maxX": 450.0, "maxY": 154.125}, "class_id": 0, "box_caption": "nomask 0.009", "scores": {"class_score": 0.00882720947265625}, "domain": "pixel"}, {"position": {"minX": 405.25, "minY": 112.8125, "maxX": 414.25, "maxY": 122.9375}, "class_id": 0, "box_caption": "nomask 0.009", "scores": {"class_score": 0.0088043212890625}, "domain": "pixel"}, {"position": {"minX": 422.0, "minY": 123.125, "maxX": 432.5, "maxY": 135.375}, "class_id": 0, "box_caption": "nomask 0.009", "scores": {"class_score": 0.00878143310546875}, "domain": "pixel"}, {"position": {"minX": 158.5, "minY": 129.625, "maxX": 170.5, "maxY": 142.875}, "class_id": 0, "box_caption": "nomask 0.009", "scores": {"class_score": 0.0087432861328125}, "domain": "pixel"}, {"position": {"minX": 322.25, "minY": 117.125, "maxX": 334.75, "maxY": 131.625}, "class_id": 1, "box_caption": "mask 0.009", "scores": {"class_score": 0.0086517333984375}, "domain": "pixel"}, {"position": {"minX": 173.625, "minY": 108.8125, "maxX": 183.375, "maxY": 119.8125}, "class_id": 0, "box_caption": "nomask 0.008", "scores": {"class_score": 0.0084991455078125}, "domain": "pixel"}, {"position": {"minX": 450.75, "minY": 146.25, "maxX": 470.25, "maxY": 168.25}, "class_id": 0, "box_caption": "nomask 0.008", "scores": {"class_score": 0.008392333984375}, "domain": "pixel"}, {"position": {"minX": 509.5, "minY": 107.875, "maxX": 523.5, "maxY": 128.375}, "class_id": 0, "box_caption": "nomask 0.008", "scores": {"class_score": 0.00838470458984375}, "domain": "pixel"}, {"position": {"minX": 452.5, "minY": 114.5, "maxX": 463.5, "maxY": 125.25}, "class_id": 0, "box_caption": "nomask 0.008", "scores": {"class_score": 0.0083465576171875}, "domain": "pixel"}, {"position": {"minX": 269.75, "minY": 140.0, "maxX": 282.25, "maxY": 155.0}, "class_id": 0, "box_caption": "nomask 0.008", "scores": {"class_score": 0.0083160400390625}, "domain": "pixel"}, {"position": {"minX": 316.0, "minY": 141.0, "maxX": 330.5, "maxY": 154.25}, "class_id": 0, "box_caption": "nomask 0.008", "scores": {"class_score": 0.00827789306640625}, "domain": "pixel"}, {"position": {"minX": 273.0, "minY": 137.0, "maxX": 288.0, "maxY": 158.5}, "class_id": 0, "box_caption": "nomask 0.008", "scores": {"class_score": 0.0081939697265625}, "domain": "pixel"}, {"position": {"minX": 249.75, "minY": 106.1875, "maxX": 263.25, "maxY": 121.4375}, "class_id": 1, "box_caption": "mask 0.008", "scores": {"class_score": 0.00818634033203125}, "domain": "pixel"}, {"position": {"minX": 160.375, "minY": 114.875, "maxX": 169.875, "maxY": 125.875}, "class_id": 0, "box_caption": "nomask 0.008", "scores": {"class_score": 0.0081329345703125}, "domain": "pixel"}, {"position": {"minX": 627.5, "minY": 199.125, "maxX": 645.5, "maxY": 218.125}, "class_id": 0, "box_caption": "nomask 0.008", "scores": {"class_score": 0.0080413818359375}, "domain": "pixel"}, {"position": {"minX": 338.25, "minY": 137.125, "maxX": 348.75, "maxY": 148.125}, "class_id": 0, "box_caption": "nomask 0.008", "scores": {"class_score": 0.00789642333984375}, "domain": "pixel"}, {"position": {"minX": 399.5, "minY": 125.25, "maxX": 419.5, "maxY": 145.25}, "class_id": 0, "box_caption": "nomask 0.008", "scores": {"class_score": 0.00780487060546875}, "domain": "pixel"}, {"position": {"minX": 195.125, "minY": 144.875, "maxX": 216.875, "maxY": 166.875}, "class_id": 0, "box_caption": "nomask 0.008", "scores": {"class_score": 0.007781982421875}, "domain": "pixel"}, {"position": {"minX": 268.75, "minY": 149.125, "maxX": 278.25, "maxY": 160.625}, "class_id": 0, "box_caption": "nomask 0.008", "scores": {"class_score": 0.007610321044921875}, "domain": "pixel"}, {"position": {"minX": 32.5, "minY": 134.25, "maxX": 41.1875, "maxY": 148.0}, "class_id": 0, "box_caption": "nomask 0.008", "scores": {"class_score": 0.007556915283203125}, "domain": "pixel"}, {"position": {"minX": 201.25, "minY": 117.5625, "maxX": 213.0, "maxY": 128.375}, "class_id": 0, "box_caption": "nomask 0.008", "scores": {"class_score": 0.007534027099609375}, "domain": "pixel"}, {"position": {"minX": 284.5, "minY": 128.875, "maxX": 298.5, "maxY": 142.625}, "class_id": 0, "box_caption": "nomask 0.007", "scores": {"class_score": 0.007415771484375}, "domain": "pixel"}, {"position": {"minX": 117.0, "minY": 175.25, "maxX": 125.875, "maxY": 185.5}, "class_id": 0, "box_caption": "nomask 0.007", "scores": {"class_score": 0.007373809814453125}, "domain": "pixel"}, {"position": {"minX": 331.75, "minY": 133.0, "maxX": 345.25, "maxY": 149.75}, "class_id": 0, "box_caption": "nomask 0.007", "scores": {"class_score": 0.007328033447265625}, "domain": "pixel"}, {"position": {"minX": 87.8125, "minY": 134.875, "maxX": 100.0625, "maxY": 147.375}, "class_id": 0, "box_caption": "nomask 0.007", "scores": {"class_score": 0.007312774658203125}, "domain": "pixel"}, {"position": {"minX": 445.0, "minY": 119.4375, "maxX": 464.5, "maxY": 138.625}, "class_id": 0, "box_caption": "nomask 0.007", "scores": {"class_score": 0.007251739501953125}, "domain": "pixel"}, {"position": {"minX": 506.5, "minY": 108.125, "maxX": 524.5, "maxY": 136.625}, "class_id": 0, "box_caption": "nomask 0.007", "scores": {"class_score": 0.00719451904296875}, "domain": "pixel"}, {"position": {"minX": 88.5625, "minY": 148.25, "maxX": 109.8125, "maxY": 181.75}, "class_id": 0, "box_caption": "nomask 0.007", "scores": {"class_score": 0.007122039794921875}, "domain": "pixel"}, {"position": {"minX": 267.25, "minY": 131.875, "maxX": 276.25, "maxY": 143.375}, "class_id": 0, "box_caption": "nomask 0.007", "scores": {"class_score": 0.00708770751953125}, "domain": "pixel"}, {"position": {"minX": 179.0, "minY": 114.25, "maxX": 188.75, "maxY": 122.875}, "class_id": 0, "box_caption": "nomask 0.007", "scores": {"class_score": 0.007030487060546875}, "domain": "pixel"}, {"position": {"minX": 25.34375, "minY": 224.375, "maxX": 40.59375, "maxY": 241.625}, "class_id": 0, "box_caption": "nomask 0.007", "scores": {"class_score": 0.006984710693359375}, "domain": "pixel"}, {"position": {"minX": 126.5, "minY": 117.875, "maxX": 143.75, "maxY": 146.625}, "class_id": 0, "box_caption": "nomask 0.007", "scores": {"class_score": 0.00689697265625}, "domain": "pixel"}, {"position": {"minX": 256.0, "minY": 165.0, "maxX": 267.5, "maxY": 175.75}, "class_id": 0, "box_caption": "nomask 0.007", "scores": {"class_score": 0.00687408447265625}, "domain": "pixel"}, {"position": {"minX": 125.75, "minY": 140.0, "maxX": 138.5, "maxY": 156.0}, "class_id": 0, "box_caption": "nomask 0.007", "scores": {"class_score": 0.006870269775390625}, "domain": "pixel"}, {"position": {"minX": 279.0, "minY": 159.625, "maxX": 290.0, "maxY": 173.375}, "class_id": 0, "box_caption": "nomask 0.007", "scores": {"class_score": 0.006626129150390625}, "domain": "pixel"}, {"position": {"minX": 201.75, "minY": 111.125, "maxX": 213.5, "maxY": 123.75}, "class_id": 0, "box_caption": "nomask 0.007", "scores": {"class_score": 0.006618499755859375}, "domain": "pixel"}, {"position": {"minX": 270.25, "minY": 147.125, "maxX": 282.75, "maxY": 162.125}, "class_id": 0, "box_caption": "nomask 0.006", "scores": {"class_score": 0.0064697265625}, "domain": "pixel"}, {"position": {"minX": 40.4375, "minY": 131.125, "maxX": 62.1875, "maxY": 149.875}, "class_id": 0, "box_caption": "nomask 0.006", "scores": {"class_score": 0.0064239501953125}, "domain": "pixel"}, {"position": {"minX": 38.75, "minY": 128.375, "maxX": 53.6875, "maxY": 142.875}, "class_id": 0, "box_caption": "nomask 0.006", "scores": {"class_score": 0.006404876708984375}, "domain": "pixel"}, {"position": {"minX": 410.25, "minY": 138.5, "maxX": 428.25, "maxY": 155.0}, "class_id": 0, "box_caption": "nomask 0.006", "scores": {"class_score": 0.006378173828125}, "domain": "pixel"}, {"position": {"minX": 180.0, "minY": 190.875, "maxX": 190.25, "maxY": 204.875}, "class_id": 0, "box_caption": "nomask 0.006", "scores": {"class_score": 0.006374359130859375}, "domain": "pixel"}, {"position": {"minX": 432.25, "minY": 139.375, "maxX": 448.75, "maxY": 159.875}, "class_id": 0, "box_caption": "nomask 0.006", "scores": {"class_score": 0.00635528564453125}, "domain": "pixel"}, {"position": {"minX": 536.5, "minY": 133.0, "maxX": 545.5, "maxY": 143.0}, "class_id": 0, "box_caption": "nomask 0.006", "scores": {"class_score": 0.006317138671875}, "domain": "pixel"}, {"position": {"minX": 445.25, "minY": 153.875, "maxX": 466.75, "maxY": 186.125}, "class_id": 0, "box_caption": "nomask 0.006", "scores": {"class_score": 0.006267547607421875}, "domain": "pixel"}, {"position": {"minX": 126.375, "minY": 123.875, "maxX": 139.375, "maxY": 137.875}, "class_id": 1, "box_caption": "mask 0.006", "scores": {"class_score": 0.006229400634765625}, "domain": "pixel"}, {"position": {"minX": 211.625, "minY": 108.625, "maxX": 222.375, "maxY": 121.125}, "class_id": 1, "box_caption": "mask 0.006", "scores": {"class_score": 0.006145477294921875}, "domain": "pixel"}, {"position": {"minX": 334.0, "minY": 137.125, "maxX": 348.0, "maxY": 155.125}, "class_id": 0, "box_caption": "nomask 0.006", "scores": {"class_score": 0.00614166259765625}, "domain": "pixel"}, {"position": {"minX": 31.65625, "minY": 127.0, "maxX": 39.78125, "maxY": 139.5}, "class_id": 0, "box_caption": "nomask 0.006", "scores": {"class_score": 0.006134033203125}, "domain": "pixel"}, {"position": {"minX": 168.125, "minY": 108.0, "maxX": 183.375, "maxY": 126.75}, "class_id": 0, "box_caption": "nomask 0.006", "scores": {"class_score": 0.006134033203125}, "domain": "pixel"}, {"position": {"minX": 18.9375, "minY": 198.0, "maxX": 36.25, "maxY": 215.5}, "class_id": 0, "box_caption": "nomask 0.006", "scores": {"class_score": 0.006031036376953125}, "domain": "pixel"}, {"position": {"minX": 363.0, "minY": 118.9375, "maxX": 380.5, "maxY": 148.0}, "class_id": 0, "box_caption": "nomask 0.006", "scores": {"class_score": 0.005985260009765625}, "domain": "pixel"}, {"position": {"minX": 59.1875, "minY": 132.5, "maxX": 71.4375, "maxY": 145.5}, "class_id": 0, "box_caption": "nomask 0.006", "scores": {"class_score": 0.005977630615234375}, "domain": "pixel"}, {"position": {"minX": 520.0, "minY": 222.125, "maxX": 526.0, "maxY": 232.875}, "class_id": 0, "box_caption": "nomask 0.006", "scores": {"class_score": 0.005977630615234375}, "domain": "pixel"}, {"position": {"minX": 238.375, "minY": 174.375, "maxX": 247.625, "maxY": 185.875}, "class_id": 0, "box_caption": "nomask 0.006", "scores": {"class_score": 0.00595855712890625}, "domain": "pixel"}, {"position": {"minX": 122.25, "minY": 141.0, "maxX": 135.0, "maxY": 155.75}, "class_id": 0, "box_caption": "nomask 0.006", "scores": {"class_score": 0.005950927734375}, "domain": "pixel"}, {"position": {"minX": 300.5, "minY": 115.875, "maxX": 309.5, "maxY": 124.75}, "class_id": 0, "box_caption": "nomask 0.006", "scores": {"class_score": 0.005931854248046875}, "domain": "pixel"}, {"position": {"minX": 335.0, "minY": 142.875, "maxX": 347.0, "maxY": 157.125}, "class_id": 0, "box_caption": "nomask 0.006", "scores": {"class_score": 0.00592803955078125}, "domain": "pixel"}, {"position": {"minX": 237.0, "minY": 198.75, "maxX": 246.5, "maxY": 210.25}, "class_id": 0, "box_caption": "nomask 0.006", "scores": {"class_score": 0.00583648681640625}, "domain": "pixel"}, {"position": {"minX": 264.75, "minY": 128.5, "maxX": 281.25, "maxY": 146.25}, "class_id": 0, "box_caption": "nomask 0.006", "scores": {"class_score": 0.00579071044921875}, "domain": "pixel"}, {"position": {"minX": 206.125, "minY": 157.75, "maxX": 217.875, "maxY": 172.5}, "class_id": 0, "box_caption": "nomask 0.006", "scores": {"class_score": 0.005718231201171875}, "domain": "pixel"}, {"position": {"minX": 130.625, "minY": 179.625, "maxX": 145.875, "maxY": 197.375}, "class_id": 0, "box_caption": "nomask 0.006", "scores": {"class_score": 0.00562286376953125}, "domain": "pixel"}, {"position": {"minX": 129.25, "minY": 159.75, "maxX": 140.25, "maxY": 171.75}, "class_id": 0, "box_caption": "nomask 0.006", "scores": {"class_score": 0.00559234619140625}, "domain": "pixel"}, {"position": {"minX": 141.125, "minY": 224.625, "maxX": 149.125, "maxY": 234.875}, "class_id": 0, "box_caption": "nomask 0.006", "scores": {"class_score": 0.005535125732421875}, "domain": "pixel"}, {"position": {"minX": 331.0, "minY": 119.75, "maxX": 341.0, "maxY": 129.625}, "class_id": 0, "box_caption": "nomask 0.005", "scores": {"class_score": 0.005462646484375}, "domain": "pixel"}, {"position": {"minX": 289.75, "minY": 116.5, "maxX": 303.25, "maxY": 132.25}, "class_id": 1, "box_caption": "mask 0.005", "scores": {"class_score": 0.0054168701171875}, "domain": "pixel"}, {"position": {"minX": 242.75, "minY": 159.75, "maxX": 252.25, "maxY": 170.0}, "class_id": 0, "box_caption": "nomask 0.005", "scores": {"class_score": 0.005397796630859375}, "domain": "pixel"}, {"position": {"minX": 627.5, "minY": 136.0, "maxX": 639.5, "maxY": 151.0}, "class_id": 0, "box_caption": "nomask 0.005", "scores": {"class_score": 0.005283355712890625}, "domain": "pixel"}, {"position": {"minX": 401.75, "minY": 114.125, "maxX": 412.75, "maxY": 124.625}, "class_id": 0, "box_caption": "nomask 0.005", "scores": {"class_score": 0.0052642822265625}, "domain": "pixel"}, {"position": {"minX": 513.0, "minY": 170.25, "maxX": 526.0, "maxY": 184.0}, "class_id": 0, "box_caption": "nomask 0.005", "scores": {"class_score": 0.00522613525390625}, "domain": "pixel"}, {"position": {"minX": 455.0, "minY": 226.875, "maxX": 462.5, "maxY": 236.625}, "class_id": 0, "box_caption": "nomask 0.005", "scores": {"class_score": 0.00522613525390625}, "domain": "pixel"}, {"position": {"minX": 305.5, "minY": 139.75, "maxX": 323.5, "maxY": 159.25}, "class_id": 0, "box_caption": "nomask 0.005", "scores": {"class_score": 0.0052032470703125}, "domain": "pixel"}, {"position": {"minX": 36.6875, "minY": 139.0, "maxX": 49.75, "maxY": 153.5}, "class_id": 0, "box_caption": "nomask 0.005", "scores": {"class_score": 0.005191802978515625}, "domain": "pixel"}, {"position": {"minX": 522.5, "minY": 168.0, "maxX": 535.5, "maxY": 185.0}, "class_id": 0, "box_caption": "nomask 0.005", "scores": {"class_score": 0.005176544189453125}, "domain": "pixel"}, {"position": {"minX": 616.0, "minY": 136.375, "maxX": 632.0, "maxY": 150.125}, "class_id": 0, "box_caption": "nomask 0.005", "scores": {"class_score": 0.005157470703125}, "domain": "pixel"}, {"position": {"minX": 266.75, "minY": 127.0, "maxX": 276.75, "maxY": 137.25}, "class_id": 0, "box_caption": "nomask 0.005", "scores": {"class_score": 0.005146026611328125}, "domain": "pixel"}, {"position": {"minX": 533.0, "minY": 134.25, "maxX": 546.0, "maxY": 151.75}, "class_id": 0, "box_caption": "nomask 0.005", "scores": {"class_score": 0.00510406494140625}, "domain": "pixel"}, {"position": {"minX": 421.75, "minY": 137.25, "maxX": 435.25, "maxY": 151.75}, "class_id": 0, "box_caption": "nomask 0.005", "scores": {"class_score": 0.005096435546875}, "domain": "pixel"}, {"position": {"minX": 78.75, "minY": 130.125, "maxX": 92.75, "maxY": 143.125}, "class_id": 0, "box_caption": "nomask 0.005", "scores": {"class_score": 0.005039215087890625}, "domain": "pixel"}, {"position": {"minX": 22.5625, "minY": 219.75, "maxX": 41.9375, "maxY": 239.5}, "class_id": 0, "box_caption": "nomask 0.005", "scores": {"class_score": 0.005023956298828125}, "domain": "pixel"}, {"position": {"minX": 33.0, "minY": 139.25, "maxX": 42.6875, "maxY": 154.5}, "class_id": 0, "box_caption": "nomask 0.005", "scores": {"class_score": 0.0049896240234375}, "domain": "pixel"}, {"position": {"minX": 127.125, "minY": 170.875, "maxX": 138.625, "maxY": 183.875}, "class_id": 0, "box_caption": "nomask 0.005", "scores": {"class_score": 0.004985809326171875}, "domain": "pixel"}, {"position": {"minX": 190.375, "minY": 139.625, "maxX": 205.875, "maxY": 156.875}, "class_id": 0, "box_caption": "nomask 0.005", "scores": {"class_score": 0.004970550537109375}, "domain": "pixel"}, {"position": {"minX": 185.375, "minY": 160.125, "maxX": 201.625, "maxY": 177.375}, "class_id": 0, "box_caption": "nomask 0.005", "scores": {"class_score": 0.004962921142578125}, "domain": "pixel"}, {"position": {"minX": 29.3125, "minY": 236.625, "maxX": 43.75, "maxY": 251.375}, "class_id": 0, "box_caption": "nomask 0.005", "scores": {"class_score": 0.00495147705078125}, "domain": "pixel"}, {"position": {"minX": 176.625, "minY": 156.625, "maxX": 187.375, "maxY": 168.375}, "class_id": 0, "box_caption": "nomask 0.005", "scores": {"class_score": 0.00494384765625}, "domain": "pixel"}, {"position": {"minX": 150.625, "minY": 159.0, "maxX": 169.625, "maxY": 180.5}, "class_id": 0, "box_caption": "nomask 0.005", "scores": {"class_score": 0.0049285888671875}, "domain": "pixel"}, {"position": {"minX": 200.0, "minY": 139.25, "maxX": 215.75, "maxY": 155.5}, "class_id": 0, "box_caption": "nomask 0.005", "scores": {"class_score": 0.004894256591796875}, "domain": "pixel"}, {"position": {"minX": 447.75, "minY": 119.6875, "maxX": 456.25, "maxY": 129.875}, "class_id": 1, "box_caption": "mask 0.005", "scores": {"class_score": 0.00489044189453125}, "domain": "pixel"}, {"position": {"minX": 20.125, "minY": 222.625, "maxX": 40.71875, "maxY": 247.875}, "class_id": 0, "box_caption": "nomask 0.005", "scores": {"class_score": 0.004886627197265625}, "domain": "pixel"}], "class_labels": {"0": "nomask", "1": "mask"}}